skillsnetwork/__init__.py
skillsnetwork/_version.py
skillsnetwork/core.py
skillsnetwork/cvstudio/__init__.py
skillsnetwork/cvstudio/__main__.py
skillsnetwork/cvstudio/download_all/__init__.py
skillsnetwork/cvstudio/download_all/__main__.py
skillsnetwork/cvstudio/download_model/__init__.py
skillsnetwork/cvstudio/download_model/__main__.py
skillsnetwork/cvstudio/ping/__init__.py
skillsnetwork/cvstudio/ping/__main__.py
skillsnetwork/cvstudio/report/__init__.py
skillsnetwork/cvstudio/report/__main__.py
skillsnetwork/cvstudio/upload_model/__init__.py
skillsnetwork/cvstudio/upload_model/__main__.py
skillsnetwork-0.21.10.dist-info/LICENSE.md
skillsnetwork-0.21.10.dist-info/METADATA
skillsnetwork-0.21.10.dist-info/WHEEL
skillsnetwork-0.21.10.dist-info/RECORD
