Metadata-Version: 2.3
Name: skillsnetwork
Version: 0.21.10
Summary: Library for working with Skills Network
License: MIT
Author: Bradley Steinfeld
Author-email: bs@ibm.com
Requires-Python: >=3.8,<4.0
Classifier: License :: OSI Approved :: MIT License
Classifier: Programming Language :: Python :: 3
Classifier: Programming Language :: Python :: 3.8
Classifier: Programming Language :: Python :: 3.9
Classifier: Programming Language :: Python :: 3.10
Classifier: Programming Language :: Python :: 3.11
Classifier: Programming Language :: Python :: 3.12
Classifier: Programming Language :: Python :: 3.13
Provides-Extra: docs
Provides-Extra: regular
Requires-Dist: Sphinx (>=4,<5) ; extra == "docs"
Requires-Dist: ibm-cos-sdk (>=2.13.3) ; extra == "regular"
Requires-Dist: ipython
Requires-Dist: ipywidgets (<=8.1.3)
Requires-Dist: pydata-sphinx-theme (>=0.9,<0.10) ; extra == "docs"
Requires-Dist: requests (>=2,<3)
Requires-Dist: sphinx-autodoc-typehints (>=1,<2) ; extra == "docs"
Requires-Dist: tqdm (>=4,<5)
Requires-Dist: typing-extensions ; (python_full_version >= "3.11.3" and python_full_version < "4.0.0") and (extra == "regular")
Project-URL: Bug Tracker, https://github.ibm.com/skills-network/labs/issues/new?assignees=&labels=bug%2C+labs&template=bug.md&title=Short+explanation+of+how+the+user+sees+the+bug+manifest
Project-URL: Repository, https://github.com/ibm-skills-network/skillsnetwork-python-library
Project-URL: Skills Network Labs, https://skills.network/lab-tools
